twisted/plugins/txsni_endpoint.py
txsni/__init__.py
txsni/only_noticed_pypi_pem_after_i_wrote_this.py
txsni/parser.py
txsni/snimap.py
txsni/tlsendpoint.py
txsni/test/__init__.py
txsni/test/test_txsni.py
txsni/test/certs/__init__.py
txsni/test/certs/cert_builder.py
TxSNI-0.2.0.dist-info/LICENSE
TxSNI-0.2.0.dist-info/METADATA
TxSNI-0.2.0.dist-info/WHEEL
TxSNI-0.2.0.dist-info/top_level.txt
TxSNI-0.2.0.dist-info/RECORD
